pytgcalls/__init__.py
pytgcalls/__version__.py
pytgcalls/environment.py
pytgcalls/exceptions.py
pytgcalls/ffmpeg.py
pytgcalls/filters.py
pytgcalls/mtproto_required.py
pytgcalls/mutex.py
pytgcalls/pytgcalls.py
pytgcalls/pytgcalls_session.py
pytgcalls/scaffold.py
pytgcalls/statictypes.py
pytgcalls/sync.py
pytgcalls/version_manager.py
pytgcalls/ytdlp.py
pytgcalls/custom_api/__init__.py
pytgcalls/custom_api/custom_api.py
pytgcalls/handlers/__init__.py
pytgcalls/handlers/handlers_holder.py
pytgcalls/media_devices/__init__.py
pytgcalls/media_devices/device_info.py
pytgcalls/media_devices/media_devices.py
pytgcalls/media_devices/screen_info.py
pytgcalls/methods/__init__.py
pytgcalls/methods/calls/__init__.py
pytgcalls/methods/calls/change_volume_call.py
pytgcalls/methods/calls/get_participants.py
pytgcalls/methods/calls/leave_call.py
pytgcalls/methods/decorators/__init__.py
pytgcalls/methods/decorators/on_update.py
pytgcalls/methods/stream/__init__.py
pytgcalls/methods/stream/mute_stream.py
pytgcalls/methods/stream/pause_stream.py
pytgcalls/methods/stream/play.py
pytgcalls/methods/stream/played_time.py
pytgcalls/methods/stream/resume_stream.py
pytgcalls/methods/stream/unmute_stream.py
pytgcalls/methods/utilities/__init__.py
pytgcalls/methods/utilities/cache_peer.py
pytgcalls/methods/utilities/call_holder.py
pytgcalls/methods/utilities/compose.py
pytgcalls/methods/utilities/cpu_usage.py
pytgcalls/methods/utilities/idle.py
pytgcalls/methods/utilities/ping.py
pytgcalls/methods/utilities/resolve_chat_id.py
pytgcalls/methods/utilities/run.py
pytgcalls/methods/utilities/start.py
pytgcalls/methods/utilities/stream_params.py
pytgcalls/mtproto/__init__.py
pytgcalls/mtproto/bridged_client.py
pytgcalls/mtproto/client_cache.py
pytgcalls/mtproto/hydrogram_client.py
pytgcalls/mtproto/mtproto_client.py
pytgcalls/mtproto/pyrogram_client.py
pytgcalls/mtproto/techgram_client.py
pytgcalls/mtproto/telethon_client.py
pytgcalls/types/__init__.py
pytgcalls/types/browsers.py
tgcall-0.0.4.dist-info/LICENSE
tgcall-0.0.4.dist-info/METADATA
tgcall-0.0.4.dist-info/WHEEL
tgcall-0.0.4.dist-info/top_level.txt
tgcall-0.0.4.dist-info/RECORD
