Metadata-Version: 2.1
Name: tgcall
Version: 0.0.4
Home-page: https://github.com/pytgcalls/pytgcalls
Author: Laky-64
Author-email: iraci.matteo@gmail.com
License: LGPL-3.0
Classifier: License :: OSI Approved :: GNU Lesser General Public License v3 (LGPLv3)
Classifier: Programming Language :: Python :: 3
Classifier: Programming Language :: Python :: 3 :: Only
Classifier: Programming Language :: Python :: 3.7
Classifier: Programming Language :: Python :: 3.8
Classifier: Programming Language :: Python :: 3.9
Classifier: Programming Language :: Python :: 3.10
Classifier: Programming Language :: Python :: 3.11
Classifier: Programming Language :: Python :: Implementation :: CPython
Classifier: Programming Language :: Python :: Implementation :: PyPy
Requires-Python: >=3.6.1
License-File: LICENSE
Requires-Dist: aiohttp
Requires-Dist: psutil
Requires-Dist: screeninfo
